converter/__init__.py
converter/console_script.py
converter/converters.py
converter/dar.py
converter/engine.py
converter/static/css/erudit/base.css
converter/static/css/erudit/pages.css
converter/static/documentation/css/style.css
converter/static/pagedjs/paged.js
converter/static/pagedjs/preview.css
converter/xsls/EruditArticle2EruditPS/main.xsl
converter/xsls/EruditArticle2EruditPS/reference_tab.xml
converter/xsls/EruditArticle2EruditPS/restriction_tab.xml
converter/xsls/EruditArticle2EruditPS/utils.xsl
converter/xsls/EruditPS2EruditArticle/main.xsl
converter/xsls/EruditPS2EruditArticle/reference_tab.xml
converter/xsls/EruditPS2EruditArticle/reference_unestructured_formated.xsl
converter/xsls/EruditPS2EruditArticle/restriction_tab.xml
converter/xsls/EruditPS2EruditArticle/utils.xsl
converter/xsls/EruditPS2HTML/main.xsl
converter/xsls/EruditPS2HTML/translations.xml
converter/xsls/EruditPS2HTML/utils.xsl
tests/__init__.py
tests/console_script_tests.py
tests/converters_eruditarticle2eruditps_tests.py
tests/converters_eruditps2eruditarticle_tests.py
tests/converters_xpath_functions_tests.py
tests/dar_tests.py
tests/engine_tests.py
xconverter-0.1.3.dist-info/LICENSE
xconverter-0.1.3.dist-info/METADATA
xconverter-0.1.3.dist-info/WHEEL
xconverter-0.1.3.dist-info/entry_points.txt
xconverter-0.1.3.dist-info/top_level.txt
xconverter-0.1.3.dist-info/RECORD
